ftllexengine/__init__.py
ftllexengine/__init__.pyi
ftllexengine/constants.py
ftllexengine/enums.py
ftllexengine/integrity.py
ftllexengine/locale_utils.py
ftllexengine/localization.py
ftllexengine/py.typed
ftllexengine/analysis/__init__.py
ftllexengine/analysis/graph.py
ftllexengine/core/__init__.py
ftllexengine/core/babel_compat.py
ftllexengine/core/depth_guard.py
ftllexengine/core/errors.py
ftllexengine/core/identifier_validation.py
ftllexengine/diagnostics/__init__.py
ftllexengine/diagnostics/codes.py
ftllexengine/diagnostics/errors.py
ftllexengine/diagnostics/formatter.py
ftllexengine/diagnostics/templates.py
ftllexengine/diagnostics/validation.py
ftllexengine/introspection/__init__.py
ftllexengine/introspection/iso.py
ftllexengine/introspection/message.py
ftllexengine/parsing/__init__.py
ftllexengine/parsing/currency.py
ftllexengine/parsing/dates.py
ftllexengine/parsing/fiscal.py
"ftllexengine/parsing/fiscal.py,cover"
ftllexengine/parsing/guards.py
ftllexengine/parsing/numbers.py
ftllexengine/runtime/__init__.py
ftllexengine/runtime/bundle.py
ftllexengine/runtime/cache.py
ftllexengine/runtime/function_bridge.py
ftllexengine/runtime/function_metadata.py
ftllexengine/runtime/functions.py
ftllexengine/runtime/locale_context.py
ftllexengine/runtime/plural_rules.py
ftllexengine/runtime/resolver.py
"ftllexengine/runtime/resolver.py,cover"
ftllexengine/runtime/rwlock.py
ftllexengine/syntax/__init__.py
ftllexengine/syntax/ast.py
ftllexengine/syntax/cursor.py
ftllexengine/syntax/position.py
ftllexengine/syntax/serializer.py
"ftllexengine/syntax/serializer.py,cover"
ftllexengine/syntax/validation_helpers.py
ftllexengine/syntax/validator.py
ftllexengine/syntax/visitor.py
ftllexengine/syntax/parser/__init__.py
ftllexengine/syntax/parser/core.py
ftllexengine/syntax/parser/primitives.py
ftllexengine/syntax/parser/rules.py
"ftllexengine/syntax/parser/rules.py,cover"
ftllexengine/syntax/parser/whitespace.py
ftllexengine/validation/__init__.py
ftllexengine-0.101.0.dist-info/METADATA
ftllexengine-0.101.0.dist-info/WHEEL
ftllexengine-0.101.0.dist-info/licenses/LICENSE
ftllexengine-0.101.0.dist-info/licenses/NOTICE
ftllexengine-0.101.0.dist-info/RECORD
