Metadata-Version: 2.4
Name: ftllexengine
Version: 0.101.0
Summary: Fluent (FTL) implementation with locale-aware parsing for numbers, dates, and currency
Project-URL: Homepage, https://github.com/resoltico/ftllexengine
Project-URL: Documentation, https://github.com/resoltico/ftllexengine#readme
Project-URL: Repository, https://github.com/resoltico/ftllexengine.git
Project-URL: Issues, https://github.com/resoltico/ftllexengine/issues
Project-URL: Changelog, https://github.com/resoltico/ftllexengine/blob/main/CHANGELOG.md
Author: Ervins Strauhmanis
License: MIT
License-File: LICENSE
License-File: NOTICE
Keywords: babel,cldr,currency,date,decimal,fluent,formatting,ftl,i18n,internationalization,l10n,locale,localization,number,parsing,plurals,thread-safe,translation
Classifier: Development Status :: 4 - Beta
Classifier: Intended Audience :: Developers
Classifier: License :: OSI Approved :: MIT License
Classifier: Operating System :: OS Independent
Classifier: Programming Language :: Python :: 3
Classifier: Programming Language :: Python :: 3 :: Only
Classifier: Programming Language :: Python :: 3.13
Classifier: Programming Language :: Python :: 3.14
Classifier: Topic :: Software Development :: Internationalization
Classifier: Topic :: Software Development :: Localization
Classifier: Topic :: Text Processing :: Linguistic
Classifier: Typing :: Typed
Requires-Python: >=3.13
Provides-Extra: babel
Requires-Dist: babel<3.0.0,>=2.17.0; extra == 'babel'
Provides-Extra: full
Requires-Dist: babel<3.0.0,>=2.17.0; extra == 'full'
